{"paths": {"admin/js/vendor/select2/i18n/af.js": "admin/js/vendor/select2/i18n/af.c4a5cbd6a23f.js", "admin/js/vendor/select2/i18n/ar.js": "admin/js/vendor/select2/i18n/ar.7dcfd5775174.js", "admin/js/vendor/select2/i18n/az.js": "admin/js/vendor/select2/i18n/az.1804c238d269.js", "admin/js/vendor/select2/i18n/bg.js": "admin/js/vendor/select2/i18n/bg.096f4410173b.js", "admin/js/vendor/select2/i18n/bn.js": "admin/js/vendor/select2/i18n/bn.b33721dc9b8a.js", "admin/js/vendor/select2/i18n/bs.js": "admin/js/vendor/select2/i18n/bs.debce43cfca2.js", "admin/js/vendor/select2/i18n/ca.js": "admin/js/vendor/select2/i18n/ca.60f20182ff18.js", "admin/js/vendor/select2/i18n/cs.js": "admin/js/vendor/select2/i18n/cs.edd7167cdcb6.js", "admin/js/vendor/select2/i18n/da.js": "admin/js/vendor/select2/i18n/da.6bbc262044b3.js", "admin/js/vendor/select2/i18n/de.js": "admin/js/vendor/select2/i18n/de.630e81c65a7b.js", "admin/js/vendor/select2/i18n/dsb.js": "admin/js/vendor/select2/i18n/dsb.9c2742bfc55a.js", "admin/js/vendor/select2/i18n/el.js": "admin/js/vendor/select2/i18n/el.01c46bf8c8b3.js", "admin/js/vendor/select2/i18n/en.js": "admin/js/vendor/select2/i18n/en.aed9bad15375.js", "admin/js/vendor/select2/i18n/es.js": "admin/js/vendor/select2/i18n/es.8b21ebdb01ee.js", "admin/js/vendor/select2/i18n/et.js": "admin/js/vendor/select2/i18n/et.32b0b17ba1a9.js", "admin/js/vendor/select2/i18n/eu.js": "admin/js/vendor/select2/i18n/eu.6c45eaf416fe.js", "admin/js/vendor/select2/i18n/fa.js": "admin/js/vendor/select2/i18n/fa.1738b003dd26.js", "admin/js/vendor/select2/i18n/fi.js": "admin/js/vendor/select2/i18n/fi.2858f3167855.js", "admin/js/vendor/select2/i18n/fr.js": "admin/js/vendor/select2/i18n/fr.6129248732b9.js", "admin/js/vendor/select2/i18n/gl.js": "admin/js/vendor/select2/i18n/gl.e2766036e78a.js", "admin/js/vendor/select2/i18n/he.js": "admin/js/vendor/select2/i18n/he.4d933538516a.js", "admin/js/vendor/select2/i18n/hi.js": "admin/js/vendor/select2/i18n/hi.f81e979ec25f.js", "admin/js/vendor/select2/i18n/hr.js": "admin/js/vendor/select2/i18n/hr.68583e607f1e.js", "admin/js/vendor/select2/i18n/hsb.js": "admin/js/vendor/select2/i18n/hsb.50caaee90a0d.js", "admin/js/vendor/select2/i18n/hu.js": "admin/js/vendor/select2/i18n/hu.9edad4c24fd0.js", "admin/js/vendor/select2/i18n/hy.js": "admin/js/vendor/select2/i18n/hy.4c655f53f4e1.js", "admin/js/vendor/select2/i18n/id.js": "admin/js/vendor/select2/i18n/id.322604a430a5.js", "admin/js/vendor/select2/i18n/is.js": "admin/js/vendor/select2/i18n/is.a8a13c9122d7.js", "admin/js/vendor/select2/i18n/it.js": "admin/js/vendor/select2/i18n/it.110a0fa84968.js", "admin/js/vendor/select2/i18n/ja.js": "admin/js/vendor/select2/i18n/ja.442146837f55.js", "admin/js/vendor/select2/i18n/ka.js": "admin/js/vendor/select2/i18n/ka.8ea0684cc301.js", "admin/js/vendor/select2/i18n/km.js": "admin/js/vendor/select2/i18n/km.8c337905305d.js", "admin/js/vendor/select2/i18n/ko.js": "admin/js/vendor/select2/i18n/ko.82358a9b6840.js", "admin/js/vendor/select2/i18n/lt.js": "admin/js/vendor/select2/i18n/lt.2c390a6bf650.js", "admin/js/vendor/select2/i18n/lv.js": "admin/js/vendor/select2/i18n/lv.30bfb7fc3b63.js", "admin/js/vendor/select2/i18n/mk.js": "admin/js/vendor/select2/i18n/mk.92f1d29581b7.js", "admin/js/vendor/select2/i18n/ms.js": "admin/js/vendor/select2/i18n/ms.ade6aba46542.js", "admin/js/vendor/select2/i18n/nb.js": "admin/js/vendor/select2/i18n/nb.e535138ca26b.js", "admin/js/vendor/select2/i18n/ne.js": "admin/js/vendor/select2/i18n/ne.f61bf00bc3fe.js", "admin/js/vendor/select2/i18n/nl.js": "admin/js/vendor/select2/i18n/nl.674c0d3da68d.js", "admin/js/vendor/select2/i18n/pl.js": "admin/js/vendor/select2/i18n/pl.a10ee9248c07.js", "admin/js/vendor/select2/i18n/ps.js": "admin/js/vendor/select2/i18n/ps.de1a40c46c09.js", "admin/js/vendor/select2/i18n/pt-BR.js": "admin/js/vendor/select2/i18n/pt-BR.455adefc2984.js", "admin/js/vendor/select2/i18n/pt.js": "admin/js/vendor/select2/i18n/pt.5b4ec8cb5b23.js", "admin/js/vendor/select2/i18n/ro.js": "admin/js/vendor/select2/i18n/ro.ea7e3b822b06.js", "admin/js/vendor/select2/i18n/ru.js": "admin/js/vendor/select2/i18n/ru.962f048c22f2.js", "admin/js/vendor/select2/i18n/sk.js": "admin/js/vendor/select2/i18n/sk.34019208b835.js", "admin/js/vendor/select2/i18n/sl.js": "admin/js/vendor/select2/i18n/sl.a5e262c643f2.js", "admin/js/vendor/select2/i18n/sq.js": "admin/js/vendor/select2/i18n/sq.abf2d34b255a.js", "admin/js/vendor/select2/i18n/sr-Cyrl.js": "admin/js/vendor/select2/i18n/sr-Cyrl.116365a2de65.js", "admin/js/vendor/select2/i18n/sr.js": "admin/js/vendor/select2/i18n/sr.c9f16b9e0f93.js", "admin/js/vendor/select2/i18n/sv.js": "admin/js/vendor/select2/i18n/sv.725800c5e8fc.js", "admin/js/vendor/select2/i18n/th.js": "admin/js/vendor/select2/i18n/th.b013804dae9c.js", "admin/js/vendor/select2/i18n/tk.js": "admin/js/vendor/select2/i18n/tk.5042dc8eca8e.js", "admin/js/vendor/select2/i18n/tr.js": "admin/js/vendor/select2/i18n/tr.dc697d893beb.js", "admin/js/vendor/select2/i18n/uk.js": "admin/js/vendor/select2/i18n/uk.e05ad5df6258.js", "admin/js/vendor/select2/i18n/vi.js": "admin/js/vendor/select2/i18n/vi.0a60056920fc.js", "admin/js/vendor/select2/i18n/zh-CN.js": "admin/js/vendor/select2/i18n/zh-CN.bde34fa3f064.js", "admin/js/vendor/select2/i18n/zh-TW.js": "admin/js/vendor/select2/i18n/zh-TW.e727260f7094.js", "applicant/assets/images/companies_logo/logo-100/logo1.jpg": "applicant/assets/images/companies_logo/logo-100/logo1.93e34c56b7ec.jpg", "applicant/assets/images/companies_logo/logo-100/logo2.jpg": "applicant/assets/images/companies_logo/logo-100/logo2.93e34c56b7ec.jpg", "applicant/assets/images/companies_logo/logo-100/logo3.jpg": "applicant/assets/images/companies_logo/logo-100/logo3.93e34c56b7ec.jpg", "applicant/assets/images/companies_logo/logo-100/logo4.jpg": "applicant/assets/images/companies_logo/logo-100/logo4.93e34c56b7ec.jpg", "applicant/assets/images/companies_logo/logo-100/logo5.jpg": "applicant/assets/images/companies_logo/logo-100/logo5.93e34c56b7ec.jpg", "applicant/assets/images/companies_logo/logo-100/logo6.jpg": "applicant/assets/images/companies_logo/logo-100/logo6.93e34c56b7ec.jpg", "applicant/assets/images/companies_logo/logo-big/logo1.jpg": "applicant/assets/images/companies_logo/logo-big/logo1.cba1451aee17.jpg", "applicant/assets/images/companies_logo/logo-big/logo2.jpg": "applicant/assets/images/companies_logo/logo-big/logo2.cba1451aee17.jpg", "applicant/assets/images/companies_logo/logo-big/logo3.jpg": "applicant/assets/images/companies_logo/logo-big/logo3.cba1451aee17.jpg", "applicant/assets/images/companies_logo/logo-big/logo4.jpg": "applicant/assets/images/companies_logo/logo-big/logo4.cba1451aee17.jpg", "applicant/assets/images/companies_logo/logo-big/logo5.jpg": "applicant/assets/images/companies_logo/logo-big/logo5.cba1451aee17.jpg", "applicant/assets/images/companies_logo/logo-small/logo1.jpg": "applicant/assets/images/companies_logo/logo-small/logo1.9232818b6084.jpg", "applicant/assets/images/companies_logo/logo-small/logo2.jpg": "applicant/assets/images/companies_logo/logo-small/logo2.9232818b6084.jpg", "applicant/assets/images/companies_logo/logo-small/logo3.jpg": "applicant/assets/images/companies_logo/logo-small/logo3.9232818b6084.jpg", "applicant/assets/images/companies_logo/logo-small/logo4.jpg": "applicant/assets/images/companies_logo/logo-small/logo4.9232818b6084.jpg", "applicant/assets/images/companies_logo/logo-small/logo5.jpg": "applicant/assets/images/companies_logo/logo-small/logo5.9232818b6084.jpg", "applicant/assets/images/product/product-big/product1.jpg": "applicant/assets/images/product/product-big/product1.bbc1bcb9c6bb.jpg", "applicant/assets/images/product/product-big/product2.jpg": "applicant/assets/images/product/product-big/product2.bbc1bcb9c6bb.jpg", "applicant/assets/images/product/product-big/product3.jpg": "applicant/assets/images/product/product-big/product3.bbc1bcb9c6bb.jpg", "applicant/assets/images/product/product-big/product4.jpg": "applicant/assets/images/product/product-big/product4.bbc1bcb9c6bb.jpg", "applicant/assets/images/product/product-big/product5.jpg": "applicant/assets/images/product/product-big/product5.bbc1bcb9c6bb.jpg", "applicant/assets/images/product/product-small/product1.jpg": "applicant/assets/images/product/product-small/product1.93e34c56b7ec.jpg", "applicant/assets/images/product/product-small/product2.jpg": "applicant/assets/images/product/product-small/product2.93e34c56b7ec.jpg", "applicant/assets/images/product/product-small/product3.jpg": "applicant/assets/images/product/product-small/product3.93e34c56b7ec.jpg", "applicant/assets/images/product/product-small/product4.jpg": "applicant/assets/images/product/product-small/product4.93e34c56b7ec.jpg", "applicant/assets/images/product/product-small/product5.jpg": "applicant/assets/images/product/product-small/product5.93e34c56b7ec.jpg", "recruiter/assets/images/companies_logo/logo-100/logo1.jpg": "recruiter/assets/images/companies_logo/logo-100/logo1.93e34c56b7ec.jpg", "recruiter/assets/images/companies_logo/logo-100/logo2.jpg": "recruiter/assets/images/companies_logo/logo-100/logo2.93e34c56b7ec.jpg", "recruiter/assets/images/companies_logo/logo-100/logo3.jpg": "recruiter/assets/images/companies_logo/logo-100/logo3.93e34c56b7ec.jpg", "recruiter/assets/images/companies_logo/logo-100/logo4.jpg": "recruiter/assets/images/companies_logo/logo-100/logo4.93e34c56b7ec.jpg", "recruiter/assets/images/companies_logo/logo-100/logo5.jpg": "recruiter/assets/images/companies_logo/logo-100/logo5.93e34c56b7ec.jpg", "recruiter/assets/images/companies_logo/logo-100/logo6.jpg": "recruiter/assets/images/companies_logo/logo-100/logo6.93e34c56b7ec.jpg", "recruiter/assets/images/companies_logo/logo-big/logo1.jpg": "recruiter/assets/images/companies_logo/logo-big/logo1.cba1451aee17.jpg", "recruiter/assets/images/companies_logo/logo-big/logo2.jpg": "recruiter/assets/images/companies_logo/logo-big/logo2.cba1451aee17.jpg", "recruiter/assets/images/companies_logo/logo-big/logo3.jpg": "recruiter/assets/images/companies_logo/logo-big/logo3.cba1451aee17.jpg", "recruiter/assets/images/companies_logo/logo-big/logo4.jpg": "recruiter/assets/images/companies_logo/logo-big/logo4.cba1451aee17.jpg", "recruiter/assets/images/companies_logo/logo-big/logo5.jpg": "recruiter/assets/images/companies_logo/logo-big/logo5.cba1451aee17.jpg", "recruiter/assets/images/companies_logo/logo-small/logo1.jpg": "recruiter/assets/images/companies_logo/logo-small/logo1.9232818b6084.jpg", "recruiter/assets/images/companies_logo/logo-small/logo2.jpg": "recruiter/assets/images/companies_logo/logo-small/logo2.9232818b6084.jpg", "recruiter/assets/images/companies_logo/logo-small/logo3.jpg": "recruiter/assets/images/companies_logo/logo-small/logo3.9232818b6084.jpg", "recruiter/assets/images/companies_logo/logo-small/logo4.jpg": "recruiter/assets/images/companies_logo/logo-small/logo4.9232818b6084.jpg", "recruiter/assets/images/companies_logo/logo-small/logo5.jpg": "recruiter/assets/images/companies_logo/logo-small/logo5.9232818b6084.jpg", "recruiter/assets/images/product/product-big/product1.jpg": "recruiter/assets/images/product/product-big/product1.bbc1bcb9c6bb.jpg", "recruiter/assets/images/product/product-big/product2.jpg": "recruiter/assets/images/product/product-big/product2.bbc1bcb9c6bb.jpg", "recruiter/assets/images/product/product-big/product3.jpg": "recruiter/assets/images/product/product-big/product3.bbc1bcb9c6bb.jpg", "recruiter/assets/images/product/product-big/product4.jpg": "recruiter/assets/images/product/product-big/product4.bbc1bcb9c6bb.jpg", "recruiter/assets/images/product/product-big/product5.jpg": "recruiter/assets/images/product/product-big/product5.bbc1bcb9c6bb.jpg", "recruiter/assets/images/product/product-small/product1.jpg": "recruiter/assets/images/product/product-small/product1.93e34c56b7ec.jpg", "recruiter/assets/images/product/product-small/product2.jpg": "recruiter/assets/images/product/product-small/product2.93e34c56b7ec.jpg", "recruiter/assets/images/product/product-small/product3.jpg": "recruiter/assets/images/product/product-small/product3.93e34c56b7ec.jpg", "recruiter/assets/images/product/product-small/product4.jpg": "recruiter/assets/images/product/product-small/product4.93e34c56b7ec.jpg", "recruiter/assets/images/product/product-small/product5.jpg": "recruiter/assets/images/product/product-small/product5.93e34c56b7ec.jpg", "admin/css/vendor/select2/LICENSE-SELECT2.md": "admin/css/vendor/select2/LICENSE-SELECT2.f94142512c91.md", "admin/css/vendor/select2/select2.css": "admin/css/vendor/select2/select2.fd9fe49d3d91.css", "admin/css/vendor/select2/select2.min.css": "admin/css/vendor/select2/select2.min.af22a7e2bfec.css", "admin/js/vendor/jquery/jquery.js": "admin/js/vendor/jquery/jquery.11c05eb286ed.js", "admin/js/vendor/jquery/jquery.min.js": "admin/js/vendor/jquery/jquery.min.220afd743d9e.js", "admin/js/vendor/jquery/LICENSE.txt": "admin/js/vendor/jquery/LICENSE.75308107741f.txt", "admin/js/vendor/select2/LICENSE.md": "admin/js/vendor/select2/LICENSE.f94142512c91.md", "admin/js/vendor/select2/select2.full.js": "admin/js/vendor/select2/select2.full.d379d5235584.js", "admin/js/vendor/select2/select2.full.min.js": "admin/js/vendor/select2/select2.full.min.68e8d8f673b7.js", "admin/js/vendor/xregexp/LICENSE.txt": "admin/js/vendor/xregexp/LICENSE.d64cecf4f157.txt", "admin/js/vendor/xregexp/xregexp.js": "admin/js/vendor/xregexp/xregexp.1865b1cf5085.js", "admin/js/vendor/xregexp/xregexp.min.js": "admin/js/vendor/xregexp/xregexp.min.c95393b8ca4d.js", "applicant/assets/css/plugins/plugins.css": "applicant/assets/css/plugins/plugins.9f796f2f1084.css", "applicant/assets/css/plugins/plugins.min.css": "applicant/assets/css/plugins/plugins.min.e40d994df3c4.css", "applicant/assets/css/vendor/bootstrap.min.css": "applicant/assets/css/vendor/bootstrap.min.cc1382088863.css", "applicant/assets/css/vendor/helper.css": "applicant/assets/css/vendor/helper.20a445eec716.css", "applicant/assets/css/vendor/iconfont.min.css": "applicant/assets/css/vendor/iconfont.min.ecec89456ea0.css", "applicant/assets/css/vendor/vendor.css": "applicant/assets/css/vendor/vendor.c4fc4afb2452.css", "applicant/assets/css/vendor/vendor.min.css": "applicant/assets/css/vendor/vendor.min.8445b000a634.css", "applicant/assets/fonts/webfonts/fa-brands-400.eot": "applicant/assets/fonts/webfonts/fa-brands-400.03783c5172ee.eot", "applicant/assets/fonts/webfonts/fa-brands-400.svg": "applicant/assets/fonts/webfonts/fa-brands-400.d1f95353a09c.svg", "applicant/assets/fonts/webfonts/fa-brands-400.ttf": "applicant/assets/fonts/webfonts/fa-brands-400.ed2b8bf11716.ttf", "applicant/assets/fonts/webfonts/fa-brands-400.woff": "applicant/assets/fonts/webfonts/fa-brands-400.fe9d62e0d16a.woff", "applicant/assets/fonts/webfonts/fa-brands-400.woff2": "applicant/assets/fonts/webfonts/fa-brands-400.7559b3774a06.woff2", "applicant/assets/fonts/webfonts/fa-regular-400.eot": "applicant/assets/fonts/webfonts/fa-regular-400.fc9c63c8224f.eot", "applicant/assets/fonts/webfonts/fa-regular-400.svg": "applicant/assets/fonts/webfonts/fa-regular-400.6c6a5fad8ed5.svg", "applicant/assets/fonts/webfonts/fa-regular-400.ttf": "applicant/assets/fonts/webfonts/fa-regular-400.59215032a439.ttf", "applicant/assets/fonts/webfonts/fa-regular-400.woff": "applicant/assets/fonts/webfonts/fa-regular-400.e5770f986396.woff", "applicant/assets/fonts/webfonts/fa-regular-400.woff2": "applicant/assets/fonts/webfonts/fa-regular-400.e07d9e40b260.woff2", "applicant/assets/fonts/webfonts/fa-solid-900.eot": "applicant/assets/fonts/webfonts/fa-solid-900.ef3df98419d1.eot", "applicant/assets/fonts/webfonts/fa-solid-900.svg": "applicant/assets/fonts/webfonts/fa-solid-900.0ffddc07ec11.svg", "applicant/assets/fonts/webfonts/fa-solid-900.ttf": "applicant/assets/fonts/webfonts/fa-solid-900.acf50f59802f.ttf", "applicant/assets/fonts/webfonts/fa-solid-900.woff": "applicant/assets/fonts/webfonts/fa-solid-900.4bced7c4c0d6.woff", "applicant/assets/fonts/webfonts/fa-solid-900.woff2": "applicant/assets/fonts/webfonts/fa-solid-900.b5cf8ae26748.woff2", "applicant/assets/images/404/bg-title-404.png": "applicant/assets/images/404/bg-title-404.8f62620fbfc5.png", "applicant/assets/images/about/bg-top-about-us.jpg": "applicant/assets/images/about/bg-top-about-us.db16b934f53c.jpg", "applicant/assets/images/app-store/app-chplay-2.png": "applicant/assets/images/app-store/app-chplay-2.22069f1f0434.png", "applicant/assets/images/app-store/app-store-2.png": "applicant/assets/images/app-store/app-store-2.22069f1f0434.png", "applicant/assets/images/author/author1.jpg": "applicant/assets/images/author/author1.bdfc6e0291c5.jpg", "applicant/assets/images/author/author2.jpg": "applicant/assets/images/author/author2.bdfc6e0291c5.jpg", "applicant/assets/images/banner/ads-three.jpg": "applicant/assets/images/banner/ads-three.61a8acab5e36.jpg", "applicant/assets/images/banner/ads-two.jpg": "applicant/assets/images/banner/ads-two.9c830c96b69a.jpg", "applicant/assets/images/banner/ads.jpg": "applicant/assets/images/banner/ads.7b9e40f1d73b.jpg", "applicant/assets/images/banner/banner-1.jpg": "applicant/assets/images/banner/banner-1.dc700b7414eb.jpg", "applicant/assets/images/banner/banner-2.jpg": "applicant/assets/images/banner/banner-2.dc700b7414eb.jpg", "applicant/assets/images/banner/banner-3.jpg": "applicant/assets/images/banner/banner-3.dc700b7414eb.jpg", "applicant/assets/images/banner/banner-4.jpg": "applicant/assets/images/banner/banner-4.dc700b7414eb.jpg", "applicant/assets/images/banner/cover-image-employer.jpg": "applicant/assets/images/banner/cover-image-employer.98c1dfb0d9e6.jpg", "applicant/assets/images/banner/job-cover.jpg": "applicant/assets/images/banner/job-cover.98c1dfb0d9e6.jpg", "applicant/assets/images/bg/banner_home_v4.png": "applicant/assets/images/bg/banner_home_v4.5f91bd463530.png", "applicant/assets/images/bg/bg_home_v2.png": "applicant/assets/images/bg/bg_home_v2.8a1e7ad83a51.png", "applicant/assets/images/bg/bg_home_v3.png": "applicant/assets/images/bg/bg_home_v3.fdcccad827fc.png", "applicant/assets/images/bg/bg_image--1.jpg": "applicant/assets/images/bg/bg_image--1.269c71f648fd.jpg", "applicant/assets/images/bg/bg_image--2.jpg": "applicant/assets/images/bg/bg_image--2.6402ace2ebbf.jpg", "applicant/assets/images/bg/bg_image--3.jpg": "applicant/assets/images/bg/bg_image--3.0451b9bef5fc.jpg", "applicant/assets/images/bg/bg_image--4.jpg": "applicant/assets/images/bg/bg_image--4.a35bc854aaa2.jpg", "applicant/assets/images/bg/bk-banner-home-4-2.png": "applicant/assets/images/bg/bk-banner-home-4-2.e0f04aa27331.png", "applicant/assets/images/bg/bk-banner-home-4-3.png": "applicant/assets/images/bg/bk-banner-home-4-3.a388531a51f7.png", "applicant/assets/images/bg/bk-banner-home-4-v1.png": "applicant/assets/images/bg/bk-banner-home-4-v1.71c28e8f5b0a.png", "applicant/assets/images/bg/bk-candidate.png": "applicant/assets/images/bg/bk-candidate.9276f5ead297.png", "applicant/assets/images/bg/bk-home-v2.png": "applicant/assets/images/bg/bk-home-v2.e75e400d75ab.png", "applicant/assets/images/bg/blog-bg-4.png": "applicant/assets/images/bg/blog-bg-4.32ef34df847c.png", "applicant/assets/images/bg/recruit.png": "applicant/assets/images/bg/recruit.e088b39cc5ce.png", "applicant/assets/images/bg/Vector-Smart-Object3.png": "applicant/assets/images/bg/Vector-Smart-Object3.d3fbdf5c0b31.png", "applicant/assets/images/blog/blog1.jpg": "applicant/assets/images/blog/blog1.06306312995b.jpg", "applicant/assets/images/blog/blog10.jpg": "applicant/assets/images/blog/blog10.7369ee1fc173.jpg", "applicant/assets/images/blog/blog2.jpg": "applicant/assets/images/blog/blog2.06306312995b.jpg", "applicant/assets/images/blog/blog3.jpg": "applicant/assets/images/blog/blog3.06306312995b.jpg", "applicant/assets/images/blog/blog4.jpg": "applicant/assets/images/blog/blog4.7369ee1fc173.jpg", "applicant/assets/images/blog/blog5.jpg": "applicant/assets/images/blog/blog5.f34e2470a7e7.jpg", "applicant/assets/images/blog/blog6.jpg": "applicant/assets/images/blog/blog6.7369ee1fc173.jpg", "applicant/assets/images/blog/blog7.jpg": "applicant/assets/images/blog/blog7.7369ee1fc173.jpg", "applicant/assets/images/blog/blog8.jpg": "applicant/assets/images/blog/blog8.7369ee1fc173.jpg", "applicant/assets/images/blog/blog9.jpg": "applicant/assets/images/blog/blog9.7369ee1fc173.jpg", "applicant/assets/images/blog/blog_08.jpg": "applicant/assets/images/blog/blog_08.7369ee1fc173.jpg", "applicant/assets/images/brand/brand-1.jpg": "applicant/assets/images/brand/brand-1.31a915c10984.jpg", "applicant/assets/images/brand/brand-1.png": "applicant/assets/images/brand/brand-1.ad42d7e4654b.png", "applicant/assets/images/brand/brand-2.jpg": "applicant/assets/images/brand/brand-2.a1ee94375ff7.jpg", "applicant/assets/images/brand/brand-2.png": "applicant/assets/images/brand/brand-2.bf906c9d04d8.png", "applicant/assets/images/brand/brand-3.jpg": "applicant/assets/images/brand/brand-3.f0f8039d8ef6.jpg", "applicant/assets/images/brand/brand-3.png": "applicant/assets/images/brand/brand-3.66c243b2f810.png", "applicant/assets/images/brand/brand-4.jpg": "applicant/assets/images/brand/brand-4.6553ee42ad93.jpg", "applicant/assets/images/brand/brand-4.png": "applicant/assets/images/brand/brand-4.d32daf87df28.png", "applicant/assets/images/brand/brand-5.jpg": "applicant/assets/images/brand/brand-5.53e83dcd8ba5.jpg", "applicant/assets/images/brand/brand-6.jpg": "applicant/assets/images/brand/brand-6.878465a33e90.jpg", "applicant/assets/images/brand/trusted-1.png": "applicant/assets/images/brand/trusted-1.99688a7e6d8b.png", "applicant/assets/images/brand/trusted-2.png": "applicant/assets/images/brand/trusted-2.a327696e6c08.png", "applicant/assets/images/brand/trusted-3.png": "applicant/assets/images/brand/trusted-3.806a46448a50.png", "applicant/assets/images/brand/trusted-4.png": "applicant/assets/images/brand/trusted-4.4c247ba0ad7c.png", "applicant/assets/images/categories/cate1.png": "applicant/assets/images/categories/cate1.142082a6023e.png", "applicant/assets/images/categories/cate2.png": "applicant/assets/images/categories/cate2.a255140d33ca.png", "applicant/assets/images/categories/cate3.png": "applicant/assets/images/categories/cate3.d76c8b694902.png", "applicant/assets/images/categories/cate4.png": "applicant/assets/images/categories/cate4.f14852056a6a.png", "applicant/assets/images/categories/cate5.png": "applicant/assets/images/categories/cate5.429c6465614d.png", "applicant/assets/images/categories/cate6.png": "applicant/assets/images/categories/cate6.97d238ef314e.png", "applicant/assets/images/categories/cate7.png": "applicant/assets/images/categories/cate7.f14852056a6a.png", "applicant/assets/images/categories/cate8.png": "applicant/assets/images/categories/cate8.6810bac13b83.png", "applicant/assets/images/companies_logo/logo-1.jpg": "applicant/assets/images/companies_logo/logo-1.c8bc0e4cbdcf.jpg", "applicant/assets/images/companies_logo/logo-10.jpg": "applicant/assets/images/companies_logo/logo-10.bdfc6e0291c5.jpg", "applicant/assets/images/companies_logo/logo-2.jpg": "applicant/assets/images/companies_logo/logo-2.bdfc6e0291c5.jpg", "applicant/assets/images/companies_logo/logo-3.jpg": "applicant/assets/images/companies_logo/logo-3.bdfc6e0291c5.jpg", "applicant/assets/images/companies_logo/logo-4.jpg": "applicant/assets/images/companies_logo/logo-4.bdfc6e0291c5.jpg", "applicant/assets/images/companies_logo/logo-5.jpg": "applicant/assets/images/companies_logo/logo-5.bdfc6e0291c5.jpg", "applicant/assets/images/companies_logo/logo-6.jpg": "applicant/assets/images/companies_logo/logo-6.bdfc6e0291c5.jpg", "applicant/assets/images/companies_logo/logo-7.jpg": "applicant/assets/images/companies_logo/logo-7.bdfc6e0291c5.jpg", "applicant/assets/images/companies_logo/logo-8.jpg": "applicant/assets/images/companies_logo/logo-8.bdfc6e0291c5.jpg", "applicant/assets/images/companies_logo/logo-9.jpg": "applicant/assets/images/companies_logo/logo-9.bdfc6e0291c5.jpg", "applicant/assets/images/employer/cover-image-employer-1.jpg": "applicant/assets/images/employer/cover-image-employer-1.5076ac9d2485.jpg", "applicant/assets/images/employer/cover-image-employer-2.jpg": "applicant/assets/images/employer/cover-image-employer-2.5076ac9d2485.jpg", "applicant/assets/images/employer/cover-image-employer-3.jpg": "applicant/assets/images/employer/cover-image-employer-3.06aac1370e1d.jpg", "applicant/assets/images/employer/cover-image-employer-4.jpg": "applicant/assets/images/employer/cover-image-employer-4.3e8a581b0b85.jpg", "applicant/assets/images/employer/cover-image-employer-5.jpg": "applicant/assets/images/employer/cover-image-employer-5.5076ac9d2485.jpg", "applicant/assets/images/hero/bg_home_01.jpg": "applicant/assets/images/hero/bg_home_01.269c71f648fd.jpg", "applicant/assets/images/icons/about1.png": "applicant/assets/images/icons/about1.476cb66a0fc0.png", "applicant/assets/images/icons/about2.png": "applicant/assets/images/icons/about2.4c84d361cba2.png", "applicant/assets/images/icons/about3.png": "applicant/assets/images/icons/about3.0814210b42d4.png", "applicant/assets/images/icons/about4.png": "applicant/assets/images/icons/about4.ef64dfa91bf4.png", "applicant/assets/images/icons/about5.png": "applicant/assets/images/icons/about5.691a5719f157.png", "applicant/assets/images/icons/about6.png": "applicant/assets/images/icons/about6.1f98977b4000.png", "applicant/assets/images/icons/candidates.png": "applicant/assets/images/icons/candidates.0da3f5daba72.png", "applicant/assets/images/icons/employers.png": "applicant/assets/images/icons/employers.3c3cceac8e17.png", "applicant/assets/images/icons/icon_apply.png": "applicant/assets/images/icons/icon_apply.671841a8e9ac.png", "applicant/assets/images/icons/icon_register_user.png": "applicant/assets/images/icons/icon_register_user.4d9de2efb408.png", "applicant/assets/images/icons/icon_search_job.png": "applicant/assets/images/icons/icon_search_job.e739e8b976f2.png", "applicant/assets/images/icons/job-applications.png": "applicant/assets/images/icons/job-applications.fb7a55ec4b2b.png", "applicant/assets/images/icons/light-close.png": "applicant/assets/images/icons/light-close.5d5fc7f28dd4.png", "applicant/assets/images/icons/total-jobs.png": "applicant/assets/images/icons/total-jobs.3daf5aef63e4.png", "applicant/assets/images/location/houston.jpg": "applicant/assets/images/location/houston.a4107d194a58.jpg", "applicant/assets/images/location/india.jpg": "applicant/assets/images/location/india.5307850dcc92.jpg", "applicant/assets/images/location/jacksonville.jpg": "applicant/assets/images/location/jacksonville.b65a0fd8eea4.jpg", "applicant/assets/images/location/petaling.jpg": "applicant/assets/images/location/petaling.65e69b352d82.jpg", "applicant/assets/images/location/Seville.jpg": "applicant/assets/images/location/Seville.b65a0fd8eea4.jpg", "applicant/assets/images/portfolio/portfolio1.jpg": "applicant/assets/images/portfolio/portfolio1.bdfc6e0291c5.jpg", "applicant/assets/images/portfolio/portfolio10.jpg": "applicant/assets/images/portfolio/portfolio10.bdfc6e0291c5.jpg", "applicant/assets/images/portfolio/portfolio2.jpg": "applicant/assets/images/portfolio/portfolio2.bdfc6e0291c5.jpg", "applicant/assets/images/portfolio/portfolio3.jpg": "applicant/assets/images/portfolio/portfolio3.bdfc6e0291c5.jpg", "applicant/assets/images/portfolio/portfolio4.jpg": "applicant/assets/images/portfolio/portfolio4.bdfc6e0291c5.jpg", "applicant/assets/images/portfolio/portfolio5.jpg": "applicant/assets/images/portfolio/portfolio5.bdfc6e0291c5.jpg", "applicant/assets/images/portfolio/portfolio6.jpg": "applicant/assets/images/portfolio/portfolio6.bdfc6e0291c5.jpg", "applicant/assets/images/portfolio/portfolio7.jpg": "applicant/assets/images/portfolio/portfolio7.bdfc6e0291c5.jpg", "applicant/assets/images/portfolio/portfolio8.jpg": "applicant/assets/images/portfolio/portfolio8.bdfc6e0291c5.jpg", "applicant/assets/images/portfolio/portfolio9.jpg": "applicant/assets/images/portfolio/portfolio9.bdfc6e0291c5.jpg", "applicant/assets/images/product/product1.jpg": "applicant/assets/images/product/product1.17a757247fb3.jpg", "applicant/assets/images/product/product10.jpg": "applicant/assets/images/product/product10.17a757247fb3.jpg", "applicant/assets/images/product/product2.jpg": "applicant/assets/images/product/product2.17a757247fb3.jpg", "applicant/assets/images/product/product3.jpg": "applicant/assets/images/product/product3.17a757247fb3.jpg", "applicant/assets/images/product/product4.jpg": "applicant/assets/images/product/product4.17a757247fb3.jpg", "applicant/assets/images/product/product5.jpg": "applicant/assets/images/product/product5.17a757247fb3.jpg", "applicant/assets/images/product/product6.jpg": "applicant/assets/images/product/product6.17a757247fb3.jpg", "applicant/assets/images/product/product7.jpg": "applicant/assets/images/product/product7.17a757247fb3.jpg", "applicant/assets/images/product/product8.jpg": "applicant/assets/images/product/product8.17a757247fb3.jpg", "applicant/assets/images/product/product9.jpg": "applicant/assets/images/product/product9.17a757247fb3.jpg", "applicant/assets/images/programming-logo/image-icon-skil-iosl.png": "applicant/assets/images/programming-logo/image-icon-skil-iosl.fe69a239d650.png", "applicant/assets/images/programming-logo/image-icon-skill-angular.png": "applicant/assets/images/programming-logo/image-icon-skill-angular.44a774250070.png", "applicant/assets/images/programming-logo/image-icon-skill-app.png": "applicant/assets/images/programming-logo/image-icon-skill-app.6db6aaef8153.png", "applicant/assets/images/programming-logo/image-icon-skill-asp.png": "applicant/assets/images/programming-logo/image-icon-skill-asp.f6c5e01724fb.png", "applicant/assets/images/programming-logo/image-icon-skill-c-plus.png": "applicant/assets/images/programming-logo/image-icon-skill-c-plus.6db6aaef8153.png", "applicant/assets/images/programming-logo/image-icon-skill-java.png": "applicant/assets/images/programming-logo/image-icon-skill-java.6db6aaef8153.png", "applicant/assets/images/programming-logo/image-icon-skill-linux.png": "applicant/assets/images/programming-logo/image-icon-skill-linux.9db9e7d55860.png", "applicant/assets/images/programming-logo/image-icon-skill-nodejs.png": "applicant/assets/images/programming-logo/image-icon-skill-nodejs.6db6aaef8153.png", "applicant/assets/images/programming-logo/image-icon-skill-python.png": "applicant/assets/images/programming-logo/image-icon-skill-python.4faf8d9afcf3.png", "applicant/assets/images/programming-logo/image-icon-skill-reactjs.png": "applicant/assets/images/programming-logo/image-icon-skill-reactjs.1eed74d01705.png", "applicant/assets/images/programming-logo/image-icon-skill-ruby.png": "applicant/assets/images/programming-logo/image-icon-skill-ruby.29f9917428a1.png", "applicant/assets/images/programming-logo/image-icon-skill-wp.png": "applicant/assets/images/programming-logo/image-icon-skill-wp.6db6aaef8153.png", "applicant/assets/images/rc-post/rc1.jpg": "applicant/assets/images/rc-post/rc1.bdfc6e0291c5.jpg", "applicant/assets/images/rc-post/rc2.jpg": "applicant/assets/images/rc-post/rc2.bdfc6e0291c5.jpg", "applicant/assets/images/rc-post/rc3.jpg": "applicant/assets/images/rc-post/rc3.bdfc6e0291c5.jpg", "applicant/assets/images/service/illus-1.jpg": "applicant/assets/images/service/illus-1.7c4cc6de973a.jpg", "applicant/assets/images/service/illus-2.jpg": "applicant/assets/images/service/illus-2.7c4cc6de973a.jpg", "applicant/assets/images/service/illus-3.jpg": "applicant/assets/images/service/illus-3.7c4cc6de973a.jpg", "applicant/assets/images/team/ab-team1.jpg": "applicant/assets/images/team/ab-team1.bdfc6e0291c5.jpg", "applicant/assets/images/team/ab-team2.jpg": "applicant/assets/images/team/ab-team2.bdfc6e0291c5.jpg", "applicant/assets/images/team/ab-team3.jpg": "applicant/assets/images/team/ab-team3.bdfc6e0291c5.jpg", "applicant/assets/images/team/ab-team4.jpg": "applicant/assets/images/team/ab-team4.bdfc6e0291c5.jpg", "applicant/assets/images/team/ab-team5.jpg": "applicant/assets/images/team/ab-team5.bdfc6e0291c5.jpg", "applicant/assets/images/team/team1.jpg": "applicant/assets/images/team/team1.e19639038f2d.jpg", "applicant/assets/images/team/team2.jpg": "applicant/assets/images/team/team2.93e34c56b7ec.jpg", "applicant/assets/images/team/team3.jpg": "applicant/assets/images/team/team3.93e34c56b7ec.jpg", "applicant/assets/images/team/team4.jpg": "applicant/assets/images/team/team4.01416ae6e32a.jpg", "applicant/assets/images/team/team5.jpg": "applicant/assets/images/team/team5.93e34c56b7ec.jpg", "applicant/assets/images/team/team6.jpg": "applicant/assets/images/team/team6.93e34c56b7ec.jpg", "applicant/assets/images/team/team7.jpg": "applicant/assets/images/team/team7.93e34c56b7ec.jpg", "applicant/assets/images/team/team8.jpg": "applicant/assets/images/team/team8.93e34c56b7ec.jpg", "applicant/assets/images/testimonial/testimoials-demo.png": "applicant/assets/images/testimonial/testimoials-demo.22d4791f5c3e.png", "applicant/assets/images/testimonial/testimonial-1.png": "applicant/assets/images/testimonial/testimonial-1.7fd367ca2466.png", "applicant/assets/images/testimonial/testimonial-2.png": "applicant/assets/images/testimonial/testimonial-2.7fd367ca2466.png", "applicant/assets/images/testimonial/testimonial-3.jpg": "applicant/assets/images/testimonial/testimonial-3.ddeff9771193.jpg", "applicant/assets/images/testimonial/testimonial-4.jpg": "applicant/assets/images/testimonial/testimonial-4.93e34c56b7ec.jpg", "applicant/assets/images/testimonial/testimonial-5.png": "applicant/assets/images/testimonial/testimonial-5.0b81b710475d.png", "applicant/assets/images/testimonial/testimonial-6.png": "applicant/assets/images/testimonial/testimonial-6.0b81b710475d.png", "applicant/assets/images/testimonial/testimonial-two-7.png": "applicant/assets/images/testimonial/testimonial-two-7.16fe497c87c0.png", "applicant/assets/images/testimonial/testimonial-two-8.png": "applicant/assets/images/testimonial/testimonial-two-8.16fe497c87c0.png", "applicant/assets/images/testimonial/testimonial-two-9.png": "applicant/assets/images/testimonial/testimonial-two-9.16fe497c87c0.png", "applicant/assets/images/video/bg-video-aboutus.jpg": "applicant/assets/images/video/bg-video-aboutus.88a191f22dab.jpg", "applicant/assets/images/work/bk-video-popup.jpg": "applicant/assets/images/work/bk-video-popup.66e7e25a4b3e.jpg", "applicant/assets/images/work/work-icon1.png": "applicant/assets/images/work/work-icon1.20d24f4abf4c.png", "applicant/assets/images/work/work-icon2.png": "applicant/assets/images/work/work-icon2.96f4abea4e10.png", "applicant/assets/images/work/work-icon3.png": "applicant/assets/images/work/work-icon3.239628dff119.png", "applicant/assets/js/plugins/plugins.js": "applicant/assets/js/plugins/plugins.525b831232d2.js", "applicant/assets/js/plugins/plugins.min.js": "applicant/assets/js/plugins/plugins.min.f0aaff6158a6.js", "applicant/assets/js/vendor/bootstrap.bundle.min.js": "applicant/assets/js/vendor/bootstrap.bundle.min.353cb81a5211.js", "applicant/assets/js/vendor/jquery-3.5.0.min.js": "applicant/assets/js/vendor/jquery-3.5.0.min.7c5d886a9449.js", "applicant/assets/js/vendor/jquery-migrate-3.1.0.min.js": "applicant/assets/js/vendor/jquery-migrate-3.1.0.min.355e4c305dd4.js", "applicant/assets/js/vendor/modernizr-3.10.0.min.js": "applicant/assets/js/vendor/modernizr-3.10.0.min.f8af6f71c60a.js", "applicant/assets/js/vendor/vendor.js": "applicant/assets/js/vendor/vendor.bcc4a883b870.js", "applicant/assets/js/vendor/vendor.min.js": "applicant/assets/js/vendor/vendor.min.6105faadb8e5.js", "recruiter/assets/css/plugins/plugins.css": "recruiter/assets/css/plugins/plugins.42c10b742853.css", "recruiter/assets/css/plugins/plugins.min.css": "recruiter/assets/css/plugins/plugins.min.e40d994df3c4.css", "recruiter/assets/css/vendor/bootstrap.min.css": "recruiter/assets/css/vendor/bootstrap.min.cc1382088863.css", "recruiter/assets/css/vendor/helper.css": "recruiter/assets/css/vendor/helper.20a445eec716.css", "recruiter/assets/css/vendor/iconfont.min.css": "recruiter/assets/css/vendor/iconfont.min.ecec89456ea0.css", "recruiter/assets/css/vendor/vendor.css": "recruiter/assets/css/vendor/vendor.c4fc4afb2452.css", "recruiter/assets/css/vendor/vendor.min.css": "recruiter/assets/css/vendor/vendor.min.8445b000a634.css", "recruiter/assets/fonts/webfonts/fa-brands-400.eot": "recruiter/assets/fonts/webfonts/fa-brands-400.03783c5172ee.eot", "recruiter/assets/fonts/webfonts/fa-brands-400.svg": "recruiter/assets/fonts/webfonts/fa-brands-400.d1f95353a09c.svg", "recruiter/assets/fonts/webfonts/fa-brands-400.ttf": "recruiter/assets/fonts/webfonts/fa-brands-400.ed2b8bf11716.ttf", "recruiter/assets/fonts/webfonts/fa-brands-400.woff": "recruiter/assets/fonts/webfonts/fa-brands-400.fe9d62e0d16a.woff", "recruiter/assets/fonts/webfonts/fa-brands-400.woff2": "recruiter/assets/fonts/webfonts/fa-brands-400.7559b3774a06.woff2", "recruiter/assets/fonts/webfonts/fa-regular-400.eot": "recruiter/assets/fonts/webfonts/fa-regular-400.fc9c63c8224f.eot", "recruiter/assets/fonts/webfonts/fa-regular-400.svg": "recruiter/assets/fonts/webfonts/fa-regular-400.6c6a5fad8ed5.svg", "recruiter/assets/fonts/webfonts/fa-regular-400.ttf": "recruiter/assets/fonts/webfonts/fa-regular-400.59215032a439.ttf", "recruiter/assets/fonts/webfonts/fa-regular-400.woff": "recruiter/assets/fonts/webfonts/fa-regular-400.e5770f986396.woff", "recruiter/assets/fonts/webfonts/fa-regular-400.woff2": "recruiter/assets/fonts/webfonts/fa-regular-400.e07d9e40b260.woff2", "recruiter/assets/fonts/webfonts/fa-solid-900.eot": "recruiter/assets/fonts/webfonts/fa-solid-900.ef3df98419d1.eot", "recruiter/assets/fonts/webfonts/fa-solid-900.svg": "recruiter/assets/fonts/webfonts/fa-solid-900.0ffddc07ec11.svg", "recruiter/assets/fonts/webfonts/fa-solid-900.ttf": "recruiter/assets/fonts/webfonts/fa-solid-900.acf50f59802f.ttf", "recruiter/assets/fonts/webfonts/fa-solid-900.woff": "recruiter/assets/fonts/webfonts/fa-solid-900.4bced7c4c0d6.woff", "recruiter/assets/fonts/webfonts/fa-solid-900.woff2": "recruiter/assets/fonts/webfonts/fa-solid-900.b5cf8ae26748.woff2", "recruiter/assets/images/404/bg-title-404.png": "recruiter/assets/images/404/bg-title-404.8f62620fbfc5.png", "recruiter/assets/images/about/bg-top-about-us.jpg": "recruiter/assets/images/about/bg-top-about-us.db16b934f53c.jpg", "recruiter/assets/images/app-store/app-chplay-2.png": "recruiter/assets/images/app-store/app-chplay-2.22069f1f0434.png", "recruiter/assets/images/app-store/app-store-2.png": "recruiter/assets/images/app-store/app-store-2.22069f1f0434.png", "recruiter/assets/images/author/author1.jpg": "recruiter/assets/images/author/author1.bdfc6e0291c5.jpg", "recruiter/assets/images/author/author2.jpg": "recruiter/assets/images/author/author2.bdfc6e0291c5.jpg", "recruiter/assets/images/banner/ads-three.jpg": "recruiter/assets/images/banner/ads-three.61a8acab5e36.jpg", "recruiter/assets/images/banner/ads-two.jpg": "recruiter/assets/images/banner/ads-two.9c830c96b69a.jpg", "recruiter/assets/images/banner/ads.jpg": "recruiter/assets/images/banner/ads.7b9e40f1d73b.jpg", "recruiter/assets/images/banner/banner-1.jpg": "recruiter/assets/images/banner/banner-1.dc700b7414eb.jpg", "recruiter/assets/images/banner/banner-2.jpg": "recruiter/assets/images/banner/banner-2.dc700b7414eb.jpg", "recruiter/assets/images/banner/banner-3.jpg": "recruiter/assets/images/banner/banner-3.dc700b7414eb.jpg", "recruiter/assets/images/banner/banner-4.jpg": "recruiter/assets/images/banner/banner-4.dc700b7414eb.jpg", "recruiter/assets/images/banner/cover-image-employer.jpg": "recruiter/assets/images/banner/cover-image-employer.98c1dfb0d9e6.jpg", "recruiter/assets/images/banner/job-cover.jpg": "recruiter/assets/images/banner/job-cover.98c1dfb0d9e6.jpg", "recruiter/assets/images/bg/banner_home_v4.png": "recruiter/assets/images/bg/banner_home_v4.5f91bd463530.png", "recruiter/assets/images/bg/bg_home_v2.png": "recruiter/assets/images/bg/bg_home_v2.8a1e7ad83a51.png", "recruiter/assets/images/bg/bg_home_v3.png": "recruiter/assets/images/bg/bg_home_v3.fdcccad827fc.png", "recruiter/assets/images/bg/bg_image--1.jpg": "recruiter/assets/images/bg/bg_image--1.269c71f648fd.jpg", "recruiter/assets/images/bg/bg_image--2.jpg": "recruiter/assets/images/bg/bg_image--2.6402ace2ebbf.jpg", "recruiter/assets/images/bg/bg_image--3.jpg": "recruiter/assets/images/bg/bg_image--3.0451b9bef5fc.jpg", "recruiter/assets/images/bg/bg_image--4.jpg": "recruiter/assets/images/bg/bg_image--4.a35bc854aaa2.jpg", "recruiter/assets/images/bg/bk-banner-home-4-2.png": "recruiter/assets/images/bg/bk-banner-home-4-2.e0f04aa27331.png", "recruiter/assets/images/bg/bk-banner-home-4-3.png": "recruiter/assets/images/bg/bk-banner-home-4-3.a388531a51f7.png", "recruiter/assets/images/bg/bk-banner-home-4-v1.png": "recruiter/assets/images/bg/bk-banner-home-4-v1.71c28e8f5b0a.png", "recruiter/assets/images/bg/bk-candidate.png": "recruiter/assets/images/bg/bk-candidate.9276f5ead297.png", "recruiter/assets/images/bg/bk-home-v2.png": "recruiter/assets/images/bg/bk-home-v2.e75e400d75ab.png", "recruiter/assets/images/bg/blog-bg-4.png": "recruiter/assets/images/bg/blog-bg-4.32ef34df847c.png", "recruiter/assets/images/bg/recruit.png": "recruiter/assets/images/bg/recruit.e088b39cc5ce.png", "recruiter/assets/images/bg/Vector-Smart-Object3.png": "recruiter/assets/images/bg/Vector-Smart-Object3.d3fbdf5c0b31.png", "recruiter/assets/images/blog/blog1.jpg": "recruiter/assets/images/blog/blog1.06306312995b.jpg", "recruiter/assets/images/blog/blog10.jpg": "recruiter/assets/images/blog/blog10.7369ee1fc173.jpg", "recruiter/assets/images/blog/blog2.jpg": "recruiter/assets/images/blog/blog2.06306312995b.jpg", "recruiter/assets/images/blog/blog3.jpg": "recruiter/assets/images/blog/blog3.06306312995b.jpg", "recruiter/assets/images/blog/blog4.jpg": "recruiter/assets/images/blog/blog4.7369ee1fc173.jpg", "recruiter/assets/images/blog/blog5.jpg": "recruiter/assets/images/blog/blog5.f34e2470a7e7.jpg", "recruiter/assets/images/blog/blog6.jpg": "recruiter/assets/images/blog/blog6.7369ee1fc173.jpg", "recruiter/assets/images/blog/blog7.jpg": "recruiter/assets/images/blog/blog7.7369ee1fc173.jpg", "recruiter/assets/images/blog/blog8.jpg": "recruiter/assets/images/blog/blog8.7369ee1fc173.jpg", "recruiter/assets/images/blog/blog9.jpg": "recruiter/assets/images/blog/blog9.7369ee1fc173.jpg", "recruiter/assets/images/blog/blog_08.jpg": "recruiter/assets/images/blog/blog_08.7369ee1fc173.jpg", "recruiter/assets/images/brand/brand-1.jpg": "recruiter/assets/images/brand/brand-1.31a915c10984.jpg", "recruiter/assets/images/brand/brand-1.png": "recruiter/assets/images/brand/brand-1.ad42d7e4654b.png", "recruiter/assets/images/brand/brand-2.jpg": "recruiter/assets/images/brand/brand-2.a1ee94375ff7.jpg", "recruiter/assets/images/brand/brand-2.png": "recruiter/assets/images/brand/brand-2.bf906c9d04d8.png", "recruiter/assets/images/brand/brand-3.jpg": "recruiter/assets/images/brand/brand-3.f0f8039d8ef6.jpg", "recruiter/assets/images/brand/brand-3.png": "recruiter/assets/images/brand/brand-3.66c243b2f810.png", "recruiter/assets/images/brand/brand-4.jpg": "recruiter/assets/images/brand/brand-4.6553ee42ad93.jpg", "recruiter/assets/images/brand/brand-4.png": "recruiter/assets/images/brand/brand-4.d32daf87df28.png", "recruiter/assets/images/brand/brand-5.jpg": "recruiter/assets/images/brand/brand-5.53e83dcd8ba5.jpg", "recruiter/assets/images/brand/brand-6.jpg": "recruiter/assets/images/brand/brand-6.878465a33e90.jpg", "recruiter/assets/images/brand/trusted-1.png": "recruiter/assets/images/brand/trusted-1.99688a7e6d8b.png", "recruiter/assets/images/brand/trusted-2.png": "recruiter/assets/images/brand/trusted-2.a327696e6c08.png", "recruiter/assets/images/brand/trusted-3.png": "recruiter/assets/images/brand/trusted-3.806a46448a50.png", "recruiter/assets/images/brand/trusted-4.png": "recruiter/assets/images/brand/trusted-4.4c247ba0ad7c.png", "recruiter/assets/images/categories/cate1.png": "recruiter/assets/images/categories/cate1.142082a6023e.png", "recruiter/assets/images/categories/cate2.png": "recruiter/assets/images/categories/cate2.a255140d33ca.png", "recruiter/assets/images/categories/cate3.png": "recruiter/assets/images/categories/cate3.d76c8b694902.png", "recruiter/assets/images/categories/cate4.png": "recruiter/assets/images/categories/cate4.f14852056a6a.png", "recruiter/assets/images/categories/cate5.png": "recruiter/assets/images/categories/cate5.429c6465614d.png", "recruiter/assets/images/categories/cate6.png": "recruiter/assets/images/categories/cate6.97d238ef314e.png", "recruiter/assets/images/categories/cate7.png": "recruiter/assets/images/categories/cate7.f14852056a6a.png", "recruiter/assets/images/categories/cate8.png": "recruiter/assets/images/categories/cate8.6810bac13b83.png", "recruiter/assets/images/companies_logo/logo-1.jpg": "recruiter/assets/images/companies_logo/logo-1.c8bc0e4cbdcf.jpg", "recruiter/assets/images/companies_logo/logo-10.jpg": "recruiter/assets/images/companies_logo/logo-10.bdfc6e0291c5.jpg", "recruiter/assets/images/companies_logo/logo-2.jpg": "recruiter/assets/images/companies_logo/logo-2.bdfc6e0291c5.jpg", "recruiter/assets/images/companies_logo/logo-3.jpg": "recruiter/assets/images/companies_logo/logo-3.bdfc6e0291c5.jpg", "recruiter/assets/images/companies_logo/logo-4.jpg": "recruiter/assets/images/companies_logo/logo-4.bdfc6e0291c5.jpg", "recruiter/assets/images/companies_logo/logo-5.jpg": "recruiter/assets/images/companies_logo/logo-5.bdfc6e0291c5.jpg", "recruiter/assets/images/companies_logo/logo-6.jpg": "recruiter/assets/images/companies_logo/logo-6.bdfc6e0291c5.jpg", "recruiter/assets/images/companies_logo/logo-7.jpg": "recruiter/assets/images/companies_logo/logo-7.bdfc6e0291c5.jpg", "recruiter/assets/images/companies_logo/logo-8.jpg": "recruiter/assets/images/companies_logo/logo-8.bdfc6e0291c5.jpg", "recruiter/assets/images/companies_logo/logo-9.jpg": "recruiter/assets/images/companies_logo/logo-9.bdfc6e0291c5.jpg", "recruiter/assets/images/employer/cover-image-employer-1.jpg": "recruiter/assets/images/employer/cover-image-employer-1.5076ac9d2485.jpg", "recruiter/assets/images/employer/cover-image-employer-2.jpg": "recruiter/assets/images/employer/cover-image-employer-2.5076ac9d2485.jpg", "recruiter/assets/images/employer/cover-image-employer-3.jpg": "recruiter/assets/images/employer/cover-image-employer-3.06aac1370e1d.jpg", "recruiter/assets/images/employer/cover-image-employer-4.jpg": "recruiter/assets/images/employer/cover-image-employer-4.3e8a581b0b85.jpg", "recruiter/assets/images/employer/cover-image-employer-5.jpg": "recruiter/assets/images/employer/cover-image-employer-5.5076ac9d2485.jpg", "recruiter/assets/images/hero/bg_home_01.jpg": "recruiter/assets/images/hero/bg_home_01.269c71f648fd.jpg", "recruiter/assets/images/icons/about1.png": "recruiter/assets/images/icons/about1.476cb66a0fc0.png", "recruiter/assets/images/icons/about2.png": "recruiter/assets/images/icons/about2.4c84d361cba2.png", "recruiter/assets/images/icons/about3.png": "recruiter/assets/images/icons/about3.0814210b42d4.png", "recruiter/assets/images/icons/about4.png": "recruiter/assets/images/icons/about4.ef64dfa91bf4.png", "recruiter/assets/images/icons/about5.png": "recruiter/assets/images/icons/about5.691a5719f157.png", "recruiter/assets/images/icons/about6.png": "recruiter/assets/images/icons/about6.1f98977b4000.png", "recruiter/assets/images/icons/candidates.png": "recruiter/assets/images/icons/candidates.0da3f5daba72.png", "recruiter/assets/images/icons/employers.png": "recruiter/assets/images/icons/employers.3c3cceac8e17.png", "recruiter/assets/images/icons/icon_apply.png": "recruiter/assets/images/icons/icon_apply.671841a8e9ac.png", "recruiter/assets/images/icons/icon_register_user.png": "recruiter/assets/images/icons/icon_register_user.4d9de2efb408.png", "recruiter/assets/images/icons/icon_search_job.png": "recruiter/assets/images/icons/icon_search_job.e739e8b976f2.png", "recruiter/assets/images/icons/job-applications.png": "recruiter/assets/images/icons/job-applications.fb7a55ec4b2b.png", "recruiter/assets/images/icons/light-close.png": "recruiter/assets/images/icons/light-close.5d5fc7f28dd4.png", "recruiter/assets/images/icons/total-jobs.png": "recruiter/assets/images/icons/total-jobs.3daf5aef63e4.png", "recruiter/assets/images/location/houston.jpg": "recruiter/assets/images/location/houston.a4107d194a58.jpg", "recruiter/assets/images/location/india.jpg": "recruiter/assets/images/location/india.5307850dcc92.jpg", "recruiter/assets/images/location/jacksonville.jpg": "recruiter/assets/images/location/jacksonville.b65a0fd8eea4.jpg", "recruiter/assets/images/location/petaling.jpg": "recruiter/assets/images/location/petaling.65e69b352d82.jpg", "recruiter/assets/images/location/Seville.jpg": "recruiter/assets/images/location/Seville.b65a0fd8eea4.jpg", "recruiter/assets/images/portfolio/portfolio1.jpg": "recruiter/assets/images/portfolio/portfolio1.bdfc6e0291c5.jpg", "recruiter/assets/images/portfolio/portfolio10.jpg": "recruiter/assets/images/portfolio/portfolio10.bdfc6e0291c5.jpg", "recruiter/assets/images/portfolio/portfolio2.jpg": "recruiter/assets/images/portfolio/portfolio2.bdfc6e0291c5.jpg", "recruiter/assets/images/portfolio/portfolio3.jpg": "recruiter/assets/images/portfolio/portfolio3.bdfc6e0291c5.jpg", "recruiter/assets/images/portfolio/portfolio4.jpg": "recruiter/assets/images/portfolio/portfolio4.bdfc6e0291c5.jpg", "recruiter/assets/images/portfolio/portfolio5.jpg": "recruiter/assets/images/portfolio/portfolio5.bdfc6e0291c5.jpg", "recruiter/assets/images/portfolio/portfolio6.jpg": "recruiter/assets/images/portfolio/portfolio6.bdfc6e0291c5.jpg", "recruiter/assets/images/portfolio/portfolio7.jpg": "recruiter/assets/images/portfolio/portfolio7.bdfc6e0291c5.jpg", "recruiter/assets/images/portfolio/portfolio8.jpg": "recruiter/assets/images/portfolio/portfolio8.bdfc6e0291c5.jpg", "recruiter/assets/images/portfolio/portfolio9.jpg": "recruiter/assets/images/portfolio/portfolio9.bdfc6e0291c5.jpg", "recruiter/assets/images/product/product1.jpg": "recruiter/assets/images/product/product1.17a757247fb3.jpg", "recruiter/assets/images/product/product10.jpg": "recruiter/assets/images/product/product10.17a757247fb3.jpg", "recruiter/assets/images/product/product2.jpg": "recruiter/assets/images/product/product2.17a757247fb3.jpg", "recruiter/assets/images/product/product3.jpg": "recruiter/assets/images/product/product3.17a757247fb3.jpg", "recruiter/assets/images/product/product4.jpg": "recruiter/assets/images/product/product4.17a757247fb3.jpg", "recruiter/assets/images/product/product5.jpg": "recruiter/assets/images/product/product5.17a757247fb3.jpg", "recruiter/assets/images/product/product6.jpg": "recruiter/assets/images/product/product6.17a757247fb3.jpg", "recruiter/assets/images/product/product7.jpg": "recruiter/assets/images/product/product7.17a757247fb3.jpg", "recruiter/assets/images/product/product8.jpg": "recruiter/assets/images/product/product8.17a757247fb3.jpg", "recruiter/assets/images/product/product9.jpg": "recruiter/assets/images/product/product9.17a757247fb3.jpg", "recruiter/assets/images/programming-logo/image-icon-skil-iosl.png": "recruiter/assets/images/programming-logo/image-icon-skil-iosl.fe69a239d650.png", "recruiter/assets/images/programming-logo/image-icon-skill-angular.png": "recruiter/assets/images/programming-logo/image-icon-skill-angular.44a774250070.png", "recruiter/assets/images/programming-logo/image-icon-skill-app.png": "recruiter/assets/images/programming-logo/image-icon-skill-app.6db6aaef8153.png", "recruiter/assets/images/programming-logo/image-icon-skill-asp.png": "recruiter/assets/images/programming-logo/image-icon-skill-asp.f6c5e01724fb.png", "recruiter/assets/images/programming-logo/image-icon-skill-c-plus.png": "recruiter/assets/images/programming-logo/image-icon-skill-c-plus.6db6aaef8153.png", "recruiter/assets/images/programming-logo/image-icon-skill-java.png": "recruiter/assets/images/programming-logo/image-icon-skill-java.6db6aaef8153.png", "recruiter/assets/images/programming-logo/image-icon-skill-linux.png": "recruiter/assets/images/programming-logo/image-icon-skill-linux.9db9e7d55860.png", "recruiter/assets/images/programming-logo/image-icon-skill-nodejs.png": "recruiter/assets/images/programming-logo/image-icon-skill-nodejs.6db6aaef8153.png", "recruiter/assets/images/programming-logo/image-icon-skill-python.png": "recruiter/assets/images/programming-logo/image-icon-skill-python.4faf8d9afcf3.png", "recruiter/assets/images/programming-logo/image-icon-skill-reactjs.png": "recruiter/assets/images/programming-logo/image-icon-skill-reactjs.1eed74d01705.png", "recruiter/assets/images/programming-logo/image-icon-skill-ruby.png": "recruiter/assets/images/programming-logo/image-icon-skill-ruby.29f9917428a1.png", "recruiter/assets/images/programming-logo/image-icon-skill-wp.png": "recruiter/assets/images/programming-logo/image-icon-skill-wp.6db6aaef8153.png", "recruiter/assets/images/rc-post/rc1.jpg": "recruiter/assets/images/rc-post/rc1.bdfc6e0291c5.jpg", "recruiter/assets/images/rc-post/rc2.jpg": "recruiter/assets/images/rc-post/rc2.bdfc6e0291c5.jpg", "recruiter/assets/images/rc-post/rc3.jpg": "recruiter/assets/images/rc-post/rc3.bdfc6e0291c5.jpg", "recruiter/assets/images/service/illus-1.jpg": "recruiter/assets/images/service/illus-1.7c4cc6de973a.jpg", "recruiter/assets/images/service/illus-2.jpg": "recruiter/assets/images/service/illus-2.7c4cc6de973a.jpg", "recruiter/assets/images/service/illus-3.jpg": "recruiter/assets/images/service/illus-3.7c4cc6de973a.jpg", "recruiter/assets/images/team/ab-team1.jpg": "recruiter/assets/images/team/ab-team1.bdfc6e0291c5.jpg", "recruiter/assets/images/team/ab-team2.jpg": "recruiter/assets/images/team/ab-team2.bdfc6e0291c5.jpg", "recruiter/assets/images/team/ab-team3.jpg": "recruiter/assets/images/team/ab-team3.bdfc6e0291c5.jpg", "recruiter/assets/images/team/ab-team4.jpg": "recruiter/assets/images/team/ab-team4.bdfc6e0291c5.jpg", "recruiter/assets/images/team/ab-team5.jpg": "recruiter/assets/images/team/ab-team5.bdfc6e0291c5.jpg", "recruiter/assets/images/team/team1.jpg": "recruiter/assets/images/team/team1.e19639038f2d.jpg", "recruiter/assets/images/team/team2.jpg": "recruiter/assets/images/team/team2.93e34c56b7ec.jpg", "recruiter/assets/images/team/team3.jpg": "recruiter/assets/images/team/team3.93e34c56b7ec.jpg", "recruiter/assets/images/team/team4.jpg": "recruiter/assets/images/team/team4.01416ae6e32a.jpg", "recruiter/assets/images/team/team5.jpg": "recruiter/assets/images/team/team5.93e34c56b7ec.jpg", "recruiter/assets/images/team/team6.jpg": "recruiter/assets/images/team/team6.93e34c56b7ec.jpg", "recruiter/assets/images/team/team7.jpg": "recruiter/assets/images/team/team7.93e34c56b7ec.jpg", "recruiter/assets/images/team/team8.jpg": "recruiter/assets/images/team/team8.93e34c56b7ec.jpg", "recruiter/assets/images/testimonial/testimoials-demo.png": "recruiter/assets/images/testimonial/testimoials-demo.22d4791f5c3e.png", "recruiter/assets/images/testimonial/testimonial-1.png": "recruiter/assets/images/testimonial/testimonial-1.7fd367ca2466.png", "recruiter/assets/images/testimonial/testimonial-2.png": "recruiter/assets/images/testimonial/testimonial-2.7fd367ca2466.png", "recruiter/assets/images/testimonial/testimonial-3.jpg": "recruiter/assets/images/testimonial/testimonial-3.ddeff9771193.jpg", "recruiter/assets/images/testimonial/testimonial-4.jpg": "recruiter/assets/images/testimonial/testimonial-4.93e34c56b7ec.jpg", "recruiter/assets/images/testimonial/testimonial-5.png": "recruiter/assets/images/testimonial/testimonial-5.0b81b710475d.png", "recruiter/assets/images/testimonial/testimonial-6.png": "recruiter/assets/images/testimonial/testimonial-6.0b81b710475d.png", "recruiter/assets/images/testimonial/testimonial-two-7.png": "recruiter/assets/images/testimonial/testimonial-two-7.16fe497c87c0.png", "recruiter/assets/images/testimonial/testimonial-two-8.png": "recruiter/assets/images/testimonial/testimonial-two-8.16fe497c87c0.png", "recruiter/assets/images/testimonial/testimonial-two-9.png": "recruiter/assets/images/testimonial/testimonial-two-9.16fe497c87c0.png", "recruiter/assets/images/video/bg-video-aboutus.jpg": "recruiter/assets/images/video/bg-video-aboutus.88a191f22dab.jpg", "recruiter/assets/images/work/bk-video-popup.jpg": "recruiter/assets/images/work/bk-video-popup.66e7e25a4b3e.jpg", "recruiter/assets/images/work/work-icon1.png": "recruiter/assets/images/work/work-icon1.20d24f4abf4c.png", "recruiter/assets/images/work/work-icon2.png": "recruiter/assets/images/work/work-icon2.96f4abea4e10.png", "recruiter/assets/images/work/work-icon3.png": "recruiter/assets/images/work/work-icon3.239628dff119.png", "recruiter/assets/js/plugins/chosen.jquery.min.js": "recruiter/assets/js/plugins/chosen.jquery.min.51cf5238a778.js", "recruiter/assets/js/plugins/plugins.js": "recruiter/assets/js/plugins/plugins.525b831232d2.js", "recruiter/assets/js/plugins/plugins.min.js": "recruiter/assets/js/plugins/plugins.min.f0aaff6158a6.js", "recruiter/assets/js/vendor/bootstrap.bundle.min.js": "recruiter/assets/js/vendor/bootstrap.bundle.min.353cb81a5211.js", "recruiter/assets/js/vendor/jquery-3.5.0.min.js": "recruiter/assets/js/vendor/jquery-3.5.0.min.7c5d886a9449.js", "recruiter/assets/js/vendor/jquery-migrate-3.1.0.min.js": "recruiter/assets/js/vendor/jquery-migrate-3.1.0.min.355e4c305dd4.js", "recruiter/assets/js/vendor/modernizr-3.10.0.min.js": "recruiter/assets/js/vendor/modernizr-3.10.0.min.f8af6f71c60a.js", "recruiter/assets/js/vendor/vendor.js": "recruiter/assets/js/vendor/vendor.bcc4a883b870.js", "recruiter/assets/js/vendor/vendor.min.js": "recruiter/assets/js/vendor/vendor.min.6105faadb8e5.js", "admin/img/gis/move_vertex_off.svg": "admin/img/gis/move_vertex_off.7a23bf31ef8a.svg", "admin/img/gis/move_vertex_on.svg": "admin/img/gis/move_vertex_on.0047eba25b67.svg", "admin/js/admin/DateTimeShortcuts.js": "admin/js/admin/DateTimeShortcuts.a9c6d180860b.js", "admin/js/admin/RelatedObjectLookups.js": "admin/js/admin/RelatedObjectLookups.ea0683bea064.js", "applicant/assets/css/applicant.css": "applicant/assets/css/applicant.7293028beacd.css", "applicant/assets/css/helper.css": "applicant/assets/css/helper.20a445eec716.css", "applicant/assets/css/style.css": "applicant/assets/css/style.0087dc79ae09.css", "applicant/assets/css/style.min-dist.css": "applicant/assets/css/style.min-dist.d3a70d587fd6.css", "applicant/assets/css/style.min.css": "applicant/assets/css/style.min.45f0cd88aa34.css", "applicant/assets/css/_dashboard.css": "applicant/assets/css/_dashboard.b0587c08dab6.css", "applicant/assets/fonts/Linearicons-Free.eot": "applicant/assets/fonts/Linearicons-Free.b9b7f23cb61b.eot", "applicant/assets/fonts/Linearicons-Free.svg": "applicant/assets/fonts/Linearicons-Free.ec161a74448c.svg", "applicant/assets/fonts/Linearicons-Free.ttf": "applicant/assets/fonts/Linearicons-Free.2f3e9f80fff7.ttf", "applicant/assets/fonts/Linearicons-Free.woff": "applicant/assets/fonts/Linearicons-Free.65060723fe96.woff", "applicant/assets/fonts/Linearicons-Free.woff2": "applicant/assets/fonts/Linearicons-Free.03e91f122aa5.woff2", "applicant/assets/images/favicon.ico": "applicant/assets/images/favicon.9c9a750812ba.ico", "applicant/assets/images/logo-blue.png": "applicant/assets/images/logo-blue.d9ec0d7056e0.png", "applicant/assets/images/logo-mobile.png": "applicant/assets/images/logo-mobile.94d4c55c739c.png", "applicant/assets/images/logo-orange.png": "applicant/assets/images/logo-orange.87e18eb01b3d.png", "applicant/assets/images/logo-purple.png": "applicant/assets/images/logo-purple.a89cdd76fda1.png", "applicant/assets/images/logo-white.png": "applicant/assets/images/logo-white.7fd0b8b6efda.png", "applicant/assets/images/logo.png": "applicant/assets/images/logo.c2b3626898ca.png", "applicant/assets/images/Toolylogo-LOGO-1A-final.png": "applicant/assets/images/Toolylogo-LOGO-1A-final.7127efa3d7b9.png", "applicant/assets/js/main.js": "applicant/assets/js/main.676c9d1718f7.js", "applicant/assets/js/modal.js": "applicant/assets/js/modal.81c132e76417.js", "applicant/assets/js/noc.js": "applicant/assets/js/noc.1b16ea0f32dd.js", "applicant/assets/js/noc_onet_data.js": "applicant/assets/js/noc_onet_data.dff9fe3dc7ee.js", "applicant/assets/php/contact-mail.php": "applicant/assets/php/contact-mail.2affe3e4bcd8.php", "applicant/assets/scss/helper.scss": "applicant/assets/scss/helper.9324912c0a29.scss", "applicant/assets/scss/style.scss": "applicant/assets/scss/style.54dcdf49a466.scss", "applicant/assets/scss/_404.scss": "applicant/assets/scss/_404.f76a4c20f863.scss", "applicant/assets/scss/_about.scss": "applicant/assets/scss/_about.75a3f41b8686.scss", "applicant/assets/scss/_banner.scss": "applicant/assets/scss/_banner.919cb13bc6ae.scss", "applicant/assets/scss/_blog.scss": "applicant/assets/scss/_blog.ab39050038dd.scss", "applicant/assets/scss/_brand.scss": "applicant/assets/scss/_brand.a04855c9d8f7.scss", "applicant/assets/scss/_candidate.scss": "applicant/assets/scss/_candidate.7b1b7bb5b6c6.scss", "applicant/assets/scss/_cart.scss": "applicant/assets/scss/_cart.3ac21f50613d.scss", "applicant/assets/scss/_categories.scss": "applicant/assets/scss/_categories.1275c387d2da.scss", "applicant/assets/scss/_checkout.scss": "applicant/assets/scss/_checkout.4a967d0ca94c.scss", "applicant/assets/scss/_color.scss": "applicant/assets/scss/_color.131cd10d49de.scss", "applicant/assets/scss/_comment.scss": "applicant/assets/scss/_comment.a7f836904d31.scss", "applicant/assets/scss/_common.scss": "applicant/assets/scss/_common.5645c8e9e420.scss", "applicant/assets/scss/_companyHistory.scss": "applicant/assets/scss/_companyHistory.cd4c3f6d8753.scss", "applicant/assets/scss/_contact.scss": "applicant/assets/scss/_contact.6fea7d1e7f10.scss", "applicant/assets/scss/_cta.scss": "applicant/assets/scss/_cta.1ae95a3c87b0.scss", "applicant/assets/scss/_dashboard.scss": "applicant/assets/scss/_dashboard.eda7623c8af6.scss", "applicant/assets/scss/_employer.scss": "applicant/assets/scss/_employer.47fcce4c2c64.scss", "applicant/assets/scss/_faq.scss": "applicant/assets/scss/_faq.d1cf615762e7.scss", "applicant/assets/scss/_feature.scss": "applicant/assets/scss/_feature.2dc829d83913.scss", "applicant/assets/scss/_footer.scss": "applicant/assets/scss/_footer.5d0f6bd73072.scss", "applicant/assets/scss/_funfact.scss": "applicant/assets/scss/_funfact.aabf9f8de81f.scss", "applicant/assets/scss/_header.scss": "applicant/assets/scss/_header.efd9e7abe9d6.scss", "applicant/assets/scss/_hero.scss": "applicant/assets/scss/_hero.ab1f89c62c32.scss", "applicant/assets/scss/_job-location.scss": "applicant/assets/scss/_job-location.2f48ebe83ca7.scss", "applicant/assets/scss/_job-search.scss": "applicant/assets/scss/_job-search.33adbe4502d3.scss", "applicant/assets/scss/_job.scss": "applicant/assets/scss/_job.8fc32ad59dbb.scss", "applicant/assets/scss/_keyword.scss": "applicant/assets/scss/_keyword.1f0e12516467.scss", "applicant/assets/scss/_login-register.scss": "applicant/assets/scss/_login-register.1652e26b1da8.scss", "applicant/assets/scss/_mixin.scss": "applicant/assets/scss/_mixin.85c4c1ab33a0.scss", "applicant/assets/scss/_mobile-menu.scss": "applicant/assets/scss/_mobile-menu.7c9dccf1b346.scss", "applicant/assets/scss/_modal.scss": "applicant/assets/scss/_modal.d7c0e3b5d416.scss", "applicant/assets/scss/_pricing.scss": "applicant/assets/scss/_pricing.3141accd70c0.scss", "applicant/assets/scss/_product.scss": "applicant/assets/scss/_product.0b6c17a89cc1.scss", "applicant/assets/scss/_recruit.scss": "applicant/assets/scss/_recruit.78cd757ac73e.scss", "applicant/assets/scss/_service.scss": "applicant/assets/scss/_service.83acb7198a48.scss", "applicant/assets/scss/_sidebar.scss": "applicant/assets/scss/_sidebar.b9b1ef25a010.scss", "applicant/assets/scss/_skill.scss": "applicant/assets/scss/_skill.0fdfd80b58a5.scss", "applicant/assets/scss/_team.scss": "applicant/assets/scss/_team.8156070fffa0.scss", "applicant/assets/scss/_testimonial.scss": "applicant/assets/scss/_testimonial.b11e3cd235fc.scss", "applicant/assets/scss/_variabls.scss": "applicant/assets/scss/_variabls.dbe8f1671f06.scss", "applicant/assets/scss/_video.scss": "applicant/assets/scss/_video.dc8680a8ba72.scss", "applicant/assets/scss/_work.scss": "applicant/assets/scss/_work.7c745235ccd9.scss", "recruiter/assets/css/chosen-sprite.png": "recruiter/assets/css/chosen-sprite.8b55a822e72b.png", "recruiter/assets/css/chosen-sprite@2x.png": "recruiter/assets/css/chosen-sprite@2x.614fad616d01.png", "recruiter/assets/css/chosen.min.css": "recruiter/assets/css/chosen.min.8122f0e0db28.css", "recruiter/assets/css/helper.css": "recruiter/assets/css/helper.20a445eec716.css", "recruiter/assets/css/recruiter.css": "recruiter/assets/css/recruiter.2c051f217161.css", "recruiter/assets/css/style.css": "recruiter/assets/css/style.0087dc79ae09.css", "recruiter/assets/css/style.min-dist.css": "recruiter/assets/css/style.min-dist.d3a70d587fd6.css", "recruiter/assets/css/style.min.css": "recruiter/assets/css/style.min.45f0cd88aa34.css", "recruiter/assets/css/_dashboard.css": "recruiter/assets/css/_dashboard.b0587c08dab6.css", "recruiter/assets/fonts/Linearicons-Free.eot": "recruiter/assets/fonts/Linearicons-Free.b9b7f23cb61b.eot", "recruiter/assets/fonts/Linearicons-Free.svg": "recruiter/assets/fonts/Linearicons-Free.ec161a74448c.svg", "recruiter/assets/fonts/Linearicons-Free.ttf": "recruiter/assets/fonts/Linearicons-Free.2f3e9f80fff7.ttf", "recruiter/assets/fonts/Linearicons-Free.woff": "recruiter/assets/fonts/Linearicons-Free.65060723fe96.woff", "recruiter/assets/fonts/Linearicons-Free.woff2": "recruiter/assets/fonts/Linearicons-Free.03e91f122aa5.woff2", "recruiter/assets/images/chosen-sprite.png": "recruiter/assets/images/chosen-sprite.8b55a822e72b.png", "recruiter/assets/images/chosen-sprite@2x.png": "recruiter/assets/images/chosen-sprite@2x.614fad616d01.png", "recruiter/assets/images/favicon.ico": "recruiter/assets/images/favicon.9c9a750812ba.ico", "recruiter/assets/images/logo-blue.png": "recruiter/assets/images/logo-blue.d9ec0d7056e0.png", "recruiter/assets/images/logo-mobile.png": "recruiter/assets/images/logo-mobile.94d4c55c739c.png", "recruiter/assets/images/logo-orange.png": "recruiter/assets/images/logo-orange.87e18eb01b3d.png", "recruiter/assets/images/logo-purple.png": "recruiter/assets/images/logo-purple.a89cdd76fda1.png", "recruiter/assets/images/logo-white.png": "recruiter/assets/images/logo-white.7fd0b8b6efda.png", "recruiter/assets/images/logo.png": "recruiter/assets/images/logo.c2b3626898ca.png", "recruiter/assets/js/filters.js": "recruiter/assets/js/filters.9354543438f5.js", "recruiter/assets/js/main.js": "recruiter/assets/js/main.246336733487.js", "recruiter/assets/php/contact-mail.php": "recruiter/assets/php/contact-mail.2affe3e4bcd8.php", "recruiter/assets/scss/helper.scss": "recruiter/assets/scss/helper.9324912c0a29.scss", "recruiter/assets/scss/style.scss": "recruiter/assets/scss/style.54dcdf49a466.scss", "recruiter/assets/scss/_404.scss": "recruiter/assets/scss/_404.f76a4c20f863.scss", "recruiter/assets/scss/_about.scss": "recruiter/assets/scss/_about.75a3f41b8686.scss", "recruiter/assets/scss/_banner.scss": "recruiter/assets/scss/_banner.919cb13bc6ae.scss", "recruiter/assets/scss/_blog.scss": "recruiter/assets/scss/_blog.ab39050038dd.scss", "recruiter/assets/scss/_brand.scss": "recruiter/assets/scss/_brand.a04855c9d8f7.scss", "recruiter/assets/scss/_candidate.scss": "recruiter/assets/scss/_candidate.7b1b7bb5b6c6.scss", "recruiter/assets/scss/_cart.scss": "recruiter/assets/scss/_cart.3ac21f50613d.scss", "recruiter/assets/scss/_categories.scss": "recruiter/assets/scss/_categories.1275c387d2da.scss", "recruiter/assets/scss/_checkout.scss": "recruiter/assets/scss/_checkout.4a967d0ca94c.scss", "recruiter/assets/scss/_color.scss": "recruiter/assets/scss/_color.131cd10d49de.scss", "recruiter/assets/scss/_comment.scss": "recruiter/assets/scss/_comment.a7f836904d31.scss", "recruiter/assets/scss/_common.scss": "recruiter/assets/scss/_common.5645c8e9e420.scss", "recruiter/assets/scss/_companyHistory.scss": "recruiter/assets/scss/_companyHistory.cd4c3f6d8753.scss", "recruiter/assets/scss/_contact.scss": "recruiter/assets/scss/_contact.6fea7d1e7f10.scss", "recruiter/assets/scss/_cta.scss": "recruiter/assets/scss/_cta.1ae95a3c87b0.scss", "recruiter/assets/scss/_dashboard.scss": "recruiter/assets/scss/_dashboard.eda7623c8af6.scss", "recruiter/assets/scss/_employer.scss": "recruiter/assets/scss/_employer.47fcce4c2c64.scss", "recruiter/assets/scss/_faq.scss": "recruiter/assets/scss/_faq.d1cf615762e7.scss", "recruiter/assets/scss/_feature.scss": "recruiter/assets/scss/_feature.2dc829d83913.scss", "recruiter/assets/scss/_footer.scss": "recruiter/assets/scss/_footer.5d0f6bd73072.scss", "recruiter/assets/scss/_funfact.scss": "recruiter/assets/scss/_funfact.aabf9f8de81f.scss", "recruiter/assets/scss/_header.scss": "recruiter/assets/scss/_header.efd9e7abe9d6.scss", "recruiter/assets/scss/_hero.scss": "recruiter/assets/scss/_hero.ab1f89c62c32.scss", "recruiter/assets/scss/_job-location.scss": "recruiter/assets/scss/_job-location.2f48ebe83ca7.scss", "recruiter/assets/scss/_job-search.scss": "recruiter/assets/scss/_job-search.33adbe4502d3.scss", "recruiter/assets/scss/_job.scss": "recruiter/assets/scss/_job.8fc32ad59dbb.scss", "recruiter/assets/scss/_keyword.scss": "recruiter/assets/scss/_keyword.1f0e12516467.scss", "recruiter/assets/scss/_login-register.scss": "recruiter/assets/scss/_login-register.1652e26b1da8.scss", "recruiter/assets/scss/_mixin.scss": "recruiter/assets/scss/_mixin.85c4c1ab33a0.scss", "recruiter/assets/scss/_mobile-menu.scss": "recruiter/assets/scss/_mobile-menu.7c9dccf1b346.scss", "recruiter/assets/scss/_modal.scss": "recruiter/assets/scss/_modal.d7c0e3b5d416.scss", "recruiter/assets/scss/_pricing.scss": "recruiter/assets/scss/_pricing.3141accd70c0.scss", "recruiter/assets/scss/_product.scss": "recruiter/assets/scss/_product.0b6c17a89cc1.scss", "recruiter/assets/scss/_recruit.scss": "recruiter/assets/scss/_recruit.78cd757ac73e.scss", "recruiter/assets/scss/_service.scss": "recruiter/assets/scss/_service.83acb7198a48.scss", "recruiter/assets/scss/_sidebar.scss": "recruiter/assets/scss/_sidebar.b9b1ef25a010.scss", "recruiter/assets/scss/_skill.scss": "recruiter/assets/scss/_skill.0fdfd80b58a5.scss", "recruiter/assets/scss/_team.scss": "recruiter/assets/scss/_team.8156070fffa0.scss", "recruiter/assets/scss/_testimonial.scss": "recruiter/assets/scss/_testimonial.b11e3cd235fc.scss", "recruiter/assets/scss/_variabls.scss": "recruiter/assets/scss/_variabls.dbe8f1671f06.scss", "recruiter/assets/scss/_video.scss": "recruiter/assets/scss/_video.dc8680a8ba72.scss", "recruiter/assets/scss/_work.scss": "recruiter/assets/scss/_work.7c745235ccd9.scss", "admin/css/autocomplete.css": "admin/css/autocomplete.781713f30664.css", "admin/css/base.css": "admin/css/base.ae33e6383baa.css", "admin/css/changelists.css": "admin/css/changelists.cfe316f81936.css", "admin/css/dashboard.css": "admin/css/dashboard.7ac78187c567.css", "admin/css/fonts.css": "admin/css/fonts.168bab448fee.css", "admin/css/forms.css": "admin/css/forms.9f1ffc442e9a.css", "admin/css/login.css": "admin/css/login.252ffabd6548.css", "admin/css/responsive.css": "admin/css/responsive.755ce0b07393.css", "admin/css/responsive_rtl.css": "admin/css/responsive_rtl.51c7445ceeff.css", "admin/css/rtl.css": "admin/css/rtl.30f903442dc5.css", "admin/css/widgets.css": "admin/css/widgets.8874c301e7bc.css", "admin/fonts/LICENSE.txt": "admin/fonts/LICENSE.d273d63619c9.txt", "admin/fonts/README.txt": "admin/fonts/README.ab99e6b541ea.txt", "admin/fonts/Roboto-Bold-webfont.woff": "admin/fonts/Roboto-Bold-webfont.50d75e48e0a3.woff", "admin/fonts/Roboto-Light-webfont.woff": "admin/fonts/Roboto-Light-webfont.c73eb1ceba33.woff", "admin/fonts/Roboto-Regular-webfont.woff": "admin/fonts/Roboto-Regular-webfont.35b07eb2f871.woff", "admin/img/calendar-icons.svg": "admin/img/calendar-icons.39b290681a8b.svg", "admin/img/icon-addlink.svg": "admin/img/icon-addlink.d519b3bab011.svg", "admin/img/icon-alert.svg": "admin/img/icon-alert.034cc7d8a67f.svg", "admin/img/icon-calendar.svg": "admin/img/icon-calendar.ac7aea671bea.svg", "admin/img/icon-changelink.svg": "admin/img/icon-changelink.18d2fd706348.svg", "admin/img/icon-clock.svg": "admin/img/icon-clock.e1d4dfac3f2b.svg", "admin/img/icon-deletelink.svg": "admin/img/icon-deletelink.564ef9dc3854.svg", "admin/img/icon-no.svg": "admin/img/icon-no.439e821418cd.svg", "admin/img/icon-unknown-alt.svg": "admin/img/icon-unknown-alt.81536e128bb6.svg", "admin/img/icon-unknown.svg": "admin/img/icon-unknown.a18cb4398978.svg", "admin/img/icon-viewlink.svg": "admin/img/icon-viewlink.41eb31f7826e.svg", "admin/img/icon-yes.svg": "admin/img/icon-yes.d2f9f035226a.svg", "admin/img/inline-delete.svg": "admin/img/inline-delete.fec1b761f254.svg", "admin/img/LICENSE": "admin/img/LICENSE.2c54f4e1ca1c", "admin/img/README.txt": "admin/img/README.a70711a38d87.txt", "admin/img/search.svg": "admin/img/search.7cf54ff789c6.svg", "admin/img/selector-icons.svg": "admin/img/selector-icons.b4555096cea2.svg", "admin/img/sorting-icons.svg": "admin/img/sorting-icons.3a097b59f104.svg", "admin/img/tooltag-add.svg": "admin/img/tooltag-add.e59d620a9742.svg", "admin/img/tooltag-arrowright.svg": "admin/img/tooltag-arrowright.bbfb788a849e.svg", "admin/js/actions.js": "admin/js/actions.8d83e3af0fbd.js", "admin/js/actions.min.js": "admin/js/actions.min.5fa8cb0403f1.js", "admin/js/autocomplete.js": "admin/js/autocomplete.cfd2c4dc8981.js", "admin/js/calendar.js": "admin/js/calendar.aae57adab5f6.js", "admin/js/cancel.js": "admin/js/cancel.a2c3149a1c5e.js", "admin/js/change_form.js": "admin/js/change_form.9e85003a1a38.js", "admin/js/collapse.js": "admin/js/collapse.c5b851e91226.js", "admin/js/collapse.min.js": "admin/js/collapse.min.44dfdb427845.js", "admin/js/core.js": "admin/js/core.ea39b3bd34c3.js", "admin/js/inlines.js": "admin/js/inlines.12d1af430335.js", "admin/js/inlines.min.js": "admin/js/inlines.min.6d6c2416646e.js", "admin/js/jquery.init.js": "admin/js/jquery.init.95b62fa19378.js", "admin/js/popup_response.js": "admin/js/popup_response.6ce3197f8fc8.js", "admin/js/prepopulate.js": "admin/js/prepopulate.2f90da7170ec.js", "admin/js/prepopulate.min.js": "admin/js/prepopulate.min.85fd5e0fb706.js", "admin/js/prepopulate_init.js": "admin/js/prepopulate_init.0d3b53c37074.js", "admin/js/SelectBox.js": "admin/js/SelectBox.99d0cfd2e80c.js", "admin/js/SelectFilter2.js": "admin/js/SelectFilter2.c26733924aea.js", "admin/js/urlify.js": "admin/js/urlify.67bae52223e0.js", "file": "file.d41d8cd98f00"}, "version": "1.0"}